{
  "last_updated": "2026-01-12T20:19:53.053Z",
  "services": {
    "Interconexão entre Data Centers (SP1 e SP2)": "operational",
    "Datacenter SP2": "operational",
    "Datacenter SP1": "operational",
    "ACS (Apache Cloud Stack)": "operational",
    "vCloud": "operational",
    "Central Telefônica": "operational",
    "Freshservice (painel de chamados)": "operational",
    "Under Control (Painel administrativo)": "operational",
    "VPN - Gerência console servidores físico Under": "operational"
  },
  "incidents": [
    {
      "title": "2",
      "status": "degraded",
      "state": "closed",
      "timestamp": "2026-01-12T20:02:08Z",
      "updated_at": "2026-01-12T20:05:42Z"
    },
    {
      "title": "",
      "status": "degraded",
      "state": "closed",
      "timestamp": "2026-01-12T19:58:46Z",
      "updated_at": "2026-01-12T20:01:49Z"
    }
  ]
}